README.md
setup.cfg
setup.py
automergetool/__init__.py
automergetool/amt.py
automergetool/amt_analyser.py
automergetool/amt_import_solver.py
automergetool/amt_launcher.py
automergetool/amt_lcs.py
automergetool/amt_utils.py
automergetool.egg-info/PKG-INFO
automergetool.egg-info/SOURCES.txt
automergetool.egg-info/dependency_links.txt
automergetool.egg-info/entry_points.txt
automergetool.egg-info/requires.txt
automergetool.egg-info/top_level.txt
automergetool/solvers/__init__.py
automergetool/solvers/gen_additions.py
automergetool/solvers/gen_debug.py
automergetool/solvers/gen_deletions.py
automergetool/solvers/gen_simplify.py
automergetool/solvers/gen_single_line.py
automergetool/solvers/gen_woven.py
automergetool/solvers/java_imports.py
automergetool/solvers/kotlin_imports.py