Metadata-Version: 1.1
Name: automergetool
Version: 0.3.0
Summary: A tool to simplify the process of solving conflicts after a git merge, rebase or cherry-pick.
Home-page: https://github.com/xgouchet/AutoMergeTool
Author: Xavier F. Gouchet
Author-email: python@xgouchet.fr
License: Apache 2.0
Keywords: git merge conflicts
Platform: UNKNOWN
Classifier: Development Status :: 4 - Beta
Classifier: Intended Audience :: Developers
Classifier: Topic :: Software Development :: Version Control :: Git
Classifier: License :: OSI Approved :: Apache Software License
Classifier: Programming Language :: Python :: 3.5
Classifier: Programming Language :: Python :: 3.6
Classifier: Programming Language :: Python :: 3.7
